rankextractplus/__init__.py
rankextractplus/main.py
rankextractplus/prompts.py
rankextractplus-2025.12.21231046.dist-info/METADATA
rankextractplus-2025.12.21231046.dist-info/WHEEL
rankextractplus-2025.12.21231046.dist-info/top_level.txt
rankextractplus-2025.12.21231046.dist-info/RECORD
