Metadata-Version: 2.4
Name: rankextractplus
Version: 2025.12.21231046
Summary: rankextractplus extracts and structures ranked info from text, organizing data for easier comparison and analysis.
Author-email: rankextractplus <hi@eugene.plus>
License: MIT
Project-URL: Homepage, https://github.com/chigwell/rankextractplus
Requires-Python: >=3.9
Requires-Dist: langchain-llm7>=0.0.0
Requires-Dist: llmatch-messages>=0.0.0
Requires-Dist: langchain-core>=0.3.0
